{
  "configVersion": 1,
  "timestamp": 1618532491425,
  "index": "/index.html",
  "assetGroups": [
    {
      "name": "app",
      "installMode": "prefetch",
      "updateMode": "prefetch",
      "cacheQueryOptions": {
        "ignoreVary": true
      },
      "urls": [
        "/favicon.ico",
        "/index.html",
        "/main-es2015.2efbf872462fee764651.js",
        "/main-es5.2efbf872462fee764651.js",
        "/manifest.webmanifest",
        "/polyfills-es2015.768ac917b54e727c4a86.js",
        "/polyfills-es5.9ab9605461190ff3297b.js",
        "/runtime-es2015.a4dadbc03350107420a4.js",
        "/runtime-es5.a4dadbc03350107420a4.js",
        "/styles.cccd6877dff65013a1b2.css"
      ],
      "patterns": []
    },
    {
      "name": "assets",
      "installMode": "lazy",
      "updateMode": "prefetch",
      "cacheQueryOptions": {
        "ignoreVary": true
      },
      "urls": [
        "/assets/icons/codepen.svg",
        "/assets/icons/facebook.svg",
        "/assets/icons/folder-open.svg",
        "/assets/icons/github.svg",
        "/assets/icons/instagram.svg",
        "/assets/icons/linkedin.svg",
        "/assets/icons/logo-128.png",
        "/assets/icons/logo-144.png",
        "/assets/icons/logo-152.png",
        "/assets/icons/logo-192.png",
        "/assets/icons/logo-384.png",
        "/assets/icons/logo-512.png",
        "/assets/icons/logo-72.png",
        "/assets/icons/logo-96.png",
        "/assets/icons/portfolio-logo.svg",
        "/assets/icons/twitter.svg",
        "/assets/styles/_partials.scss",
        "/assets/styles/modules/_theme.scss",
        "/assets/styles/partials/_card.scss",
        "/assets/styles/partials/_layout.scss",
        "/assets/styles/partials/_link.scss",
        "/assets/styles/partials/_theme.scss"
      ],
      "patterns": []
    }
  ],
  "dataGroups": [],
  "hashTable": {
    "/assets/icons/codepen.svg": "440ce50b87e0f25f5a98b64e8d9456249697cc69",
    "/assets/icons/facebook.svg": "9047a49e14ed3e8d120c07f30070ad92a70447a4",
    "/assets/icons/folder-open.svg": "9a9365052cc9582c0008a3dc42833ab0862f5c25",
    "/assets/icons/github.svg": "ee58bd52af4b2c26ed6b172de6e10d748a7d9f66",
    "/assets/icons/instagram.svg": "e73e46c8be1149b5d9218788b4635410adb7c785",
    "/assets/icons/linkedin.svg": "77694cfb84d5467de08603d748b7076aad28db90",
    "/assets/icons/logo-128.png": "19a05b5456165fff2d74aa66753a1e2823306f06",
    "/assets/icons/logo-144.png": "9ee5035896b6201b22fa169d1735cb916757155b",
    "/assets/icons/logo-152.png": "496d8c9c79e4b6ff344acc4b75e9082a31aad6cb",
    "/assets/icons/logo-192.png": "b288c29835b8f47dca69a1a78bdbd65e859ec0a0",
    "/assets/icons/logo-384.png": "13332b2c583e64cb22603815abae3f99e61fea60",
    "/assets/icons/logo-512.png": "3188bb97ca00d36421bbb597283860e30e295bec",
    "/assets/icons/logo-72.png": "8a6147658504a5d14b74f0eb80364d37a72bc1d3",
    "/assets/icons/logo-96.png": "48d349b88b48157509cb0d6ef09eedf6efe20f98",
    "/assets/icons/portfolio-logo.svg": "b51714f56e9884fa3d0452d7bfa8ac39a9174cb0",
    "/assets/icons/twitter.svg": "f98ae5763bac8e178b70acef86a505708c4a5f83",
    "/assets/styles/_partials.scss": "603bcf1743d1e3aed0b47d2d70060fe9d7d38c6a",
    "/assets/styles/modules/_theme.scss": "9a9fd1ed6cffe6be053c3eb3cced49c589f3bbcc",
    "/assets/styles/partials/_card.scss": "64446d697b5c2a4c72401d94f4f4dd267c0ce475",
    "/assets/styles/partials/_layout.scss": "498656784e45c85a119a4027fed35069a6b917e1",
    "/assets/styles/partials/_link.scss": "6361fba778060d66422a72beb4b40df5a108b925",
    "/assets/styles/partials/_theme.scss": "59dc280f2f92d6d8564d5645faca25f6b485cae2",
    "/favicon.ico": "22f6a4a3bcaafafb0254e0f2fa4ceb89e505e8b2",
    "/index.html": "463a2f4727991f28b2e9e1718d2fd81918ce538a",
    "/main-es2015.2efbf872462fee764651.js": "855e9527485032ea1253ab05e2aef11f96e1c93a",
    "/main-es5.2efbf872462fee764651.js": "c08f27aa2ef70af99acf4b4833489ee564e6635d",
    "/manifest.webmanifest": "828dc2a44155dd7d91fe43dcd0a3221218c2dab1",
    "/polyfills-es2015.768ac917b54e727c4a86.js": "c0bfc31b431b81064dd1537bc990cd6352b0d36d",
    "/polyfills-es5.9ab9605461190ff3297b.js": "70de5c3c9763accf11de169aa6784abd01326edc",
    "/runtime-es2015.a4dadbc03350107420a4.js": "a9aafcf49f49145093fc831efd9b8e2f6c71bb9c",
    "/runtime-es5.a4dadbc03350107420a4.js": "a9aafcf49f49145093fc831efd9b8e2f6c71bb9c",
    "/styles.cccd6877dff65013a1b2.css": "05767d4248c67e6e0abc0f6e27c9a5d694f992d8"
  },
  "navigationUrls": [
    {
      "positive": true,
      "regex": "^\\/.*$"
    },
    {
      "positive": false,
      "regex": "^\\/(?:.+\\/)?[^/]*\\.[^/]*$"
    },
    {
      "positive": false,
      "regex": "^\\/(?:.+\\/)?[^/]*__[^/]*$"
    },
    {
      "positive": false,
      "regex": "^\\/(?:.+\\/)?[^/]*__[^/]*\\/.*$"
    }
  ],
  "navigationRequestStrategy": "performance"
}