{
  "configVersion": 1,
  "timestamp": 1641662821422,
  "index": "/index.html",
  "assetGroups": [
    {
      "name": "app",
      "installMode": "prefetch",
      "updateMode": "prefetch",
      "cacheQueryOptions": {
        "ignoreVary": true
      },
      "urls": [
        "/favicon.ico",
        "/index.html",
        "/main.6cd55df2245c00dc.js",
        "/manifest.webmanifest",
        "/polyfills.a1956e7d60edaab0.js",
        "/runtime.be02ce8f435064c9.js",
        "/styles.1f89df64f54779fe.css"
      ],
      "patterns": []
    },
    {
      "name": "assets",
      "installMode": "lazy",
      "updateMode": "prefetch",
      "cacheQueryOptions": {
        "ignoreVary": true
      },
      "urls": [
        "/assets/icons/codepen.svg",
        "/assets/icons/facebook.svg",
        "/assets/icons/folder-open.svg",
        "/assets/icons/github.svg",
        "/assets/icons/instagram.svg",
        "/assets/icons/linkedin.svg",
        "/assets/icons/logo-128.png",
        "/assets/icons/logo-144.png",
        "/assets/icons/logo-152.png",
        "/assets/icons/logo-192.png",
        "/assets/icons/logo-384.png",
        "/assets/icons/logo-512.png",
        "/assets/icons/logo-72.png",
        "/assets/icons/logo-96.png",
        "/assets/icons/portfolio-logo.svg",
        "/assets/icons/twitter.svg",
        "/assets/styles/_partials.scss",
        "/assets/styles/modules/_theme.scss",
        "/assets/styles/partials/_card.scss",
        "/assets/styles/partials/_layout.scss",
        "/assets/styles/partials/_link.scss",
        "/assets/styles/partials/_theme.scss"
      ],
      "patterns": []
    }
  ],
  "dataGroups": [],
  "hashTable": {
    "/assets/icons/codepen.svg": "440ce50b87e0f25f5a98b64e8d9456249697cc69",
    "/assets/icons/facebook.svg": "9047a49e14ed3e8d120c07f30070ad92a70447a4",
    "/assets/icons/folder-open.svg": "9a9365052cc9582c0008a3dc42833ab0862f5c25",
    "/assets/icons/github.svg": "ee58bd52af4b2c26ed6b172de6e10d748a7d9f66",
    "/assets/icons/instagram.svg": "e73e46c8be1149b5d9218788b4635410adb7c785",
    "/assets/icons/linkedin.svg": "77694cfb84d5467de08603d748b7076aad28db90",
    "/assets/icons/logo-128.png": "19a05b5456165fff2d74aa66753a1e2823306f06",
    "/assets/icons/logo-144.png": "9ee5035896b6201b22fa169d1735cb916757155b",
    "/assets/icons/logo-152.png": "496d8c9c79e4b6ff344acc4b75e9082a31aad6cb",
    "/assets/icons/logo-192.png": "b288c29835b8f47dca69a1a78bdbd65e859ec0a0",
    "/assets/icons/logo-384.png": "13332b2c583e64cb22603815abae3f99e61fea60",
    "/assets/icons/logo-512.png": "3188bb97ca00d36421bbb597283860e30e295bec",
    "/assets/icons/logo-72.png": "8a6147658504a5d14b74f0eb80364d37a72bc1d3",
    "/assets/icons/logo-96.png": "48d349b88b48157509cb0d6ef09eedf6efe20f98",
    "/assets/icons/portfolio-logo.svg": "1e32aebe9f1b3cee810eac4401e2c1b2dc563324",
    "/assets/icons/twitter.svg": "f98ae5763bac8e178b70acef86a505708c4a5f83",
    "/assets/styles/_partials.scss": "25ac8cfa1b1ed432c1d35ddc5dcc654d1fb4074e",
    "/assets/styles/modules/_theme.scss": "e1ea7181a057d1b34e3bb96b24ca4f966638407f",
    "/assets/styles/partials/_card.scss": "be6fd19164b74925f5920067adeff6b7c7cafcca",
    "/assets/styles/partials/_layout.scss": "2cc59e3c773a8be111d6adcfb669bc7f266079dd",
    "/assets/styles/partials/_link.scss": "3dbc0307a607c29c519b08b72a14a8920db4b08a",
    "/assets/styles/partials/_theme.scss": "1e3dd7848c9df1faa13b1faa48c84435e4ebe5f2",
    "/favicon.ico": "22f6a4a3bcaafafb0254e0f2fa4ceb89e505e8b2",
    "/index.html": "b43db7033b30a63253ea934862da7d68410a33e5",
    "/main.6cd55df2245c00dc.js": "8bc49560e048761dfc9862d7a010b83c5ebc06c5",
    "/manifest.webmanifest": "e9a63dc37a012bf9c93022b76dcc698ca3a32766",
    "/polyfills.a1956e7d60edaab0.js": "6786762bf9ccbf17a6e8e4effdb1a6334c3fb8b9",
    "/runtime.be02ce8f435064c9.js": "fd561afeeeea810c7b726244fe9f8c931efea600",
    "/styles.1f89df64f54779fe.css": "f3ce0f9d1f24326f3117f1e0eeec9c83a688577d"
  },
  "navigationUrls": [
    {
      "positive": true,
      "regex": "^\\/.*$"
    },
    {
      "positive": false,
      "regex": "^\\/(?:.+\\/)?[^/]*\\.[^/]*$"
    },
    {
      "positive": false,
      "regex": "^\\/(?:.+\\/)?[^/]*__[^/]*$"
    },
    {
      "positive": false,
      "regex": "^\\/(?:.+\\/)?[^/]*__[^/]*\\/.*$"
    }
  ],
  "navigationRequestStrategy": "performance"
}